cftool/__init__.py
cftool/cftool.py
cftool/compile.py
cftool/html.py
cftool/prefs.json
cftool/run.py
cftool/save.py
cftool-1.0.4.dist-info/DESCRIPTION.rst
cftool-1.0.4.dist-info/METADATA
cftool-1.0.4.dist-info/RECORD
cftool-1.0.4.dist-info/WHEEL
cftool-1.0.4.dist-info/entry_points.txt
cftool-1.0.4.dist-info/metadata.json
cftool-1.0.4.dist-info/top_level.txt
