Metadata-Version: 2.0
Name: cftool
Version: 1.0.4
Summary: Get inputs and outputs from Codeforces and others online judges
Home-page: https://github.com/guilhermeleobas/cftool
Author: Guilherme Leobas
Author-email: UNKNOWN
License: MIT
Keywords: Codeforces
Platform: UNKNOWN
Requires-Dist: beautifulsoup4 (==4.4.1)
Requires-Dist: colorama (==0.3.7)
Requires-Dist: requests (==2.10.0)
